README.md
setup.cfg
setup.py
cocoyoyo_librairie_api/__init__.py
cocoyoyo_librairie_api/api.py
cocoyoyo_librairie_api/getting_started.py
cocoyoyo_librairie_api.egg-info/PKG-INFO
cocoyoyo_librairie_api.egg-info/SOURCES.txt
cocoyoyo_librairie_api.egg-info/dependency_links.txt
cocoyoyo_librairie_api.egg-info/requires.txt
cocoyoyo_librairie_api.egg-info/top_level.txt