Metadata-Version: 2.1
Name: cocoyoyo-librairie-api
Version: 2.0.0
Summary: Official CocoyoyoLibrairie API packages
Home-page: UNKNOWN
Author: CAMARM-DEV
Author-email: armand@camponovo.xyz
License: MIT
Keywords: conversion
Platform: UNKNOWN
Classifier: Development Status :: 5 - Production/Stable
Classifier: Intended Audience :: Developers
Classifier: License :: OSI Approved :: MIT License
Classifier: Programming Language :: Python :: 3
